[
  {
    "verse": [
      {
        "i": 0,
        "word": "Ὁ",
        "text": "The"
      },
      {
        "i": 1,
        "word": "πρεσβύτερος",
        "text": "elder"
      },
      {
        "i": 2,
        "word": "ἐκλεκτῇ",
        "text": "To [the] elect"
      },
      {
        "i": 3,
        "word": "κυρίᾳ",
        "text": "lady"
      },
      {
        "i": 4,
        "word": "καὶ",
        "text": "and"
      },
      {
        "i": 5,
        "word": "τοῖς",
        "text": "the"
      },
      {
        "i": 6,
        "word": "τέκνοις",
        "text": "children"
      },
      {
        "i": 7,
        "word": "αὐτῆς",
        "text": "of her"
      },
      {
        "i": 8,
        "word": "οὓς",
        "text": "whom"
      },
      {
        "i": 9,
        "word": "ἐγὼ",
        "text": "I"
      },
      {
        "i": 10,
        "word": "ἀγαπῶ",
        "text": "love"
      },
      {
        "i": 11,
        "word": "ἐν",
        "text": "in"
      },
      {
        "i": 12,
        "word": "ἀληθείᾳ",
        "text": "truth"
      },
      {
        "i": 13,
        "word": "καὶ",
        "text": "and"
      },
      {
        "i": 14,
        "word": "οὐκ",
        "text": "not"
      },
      {
        "i": 15,
        "word": "ἐγὼ",
        "text": "I"
      },
      {
        "i": 16,
        "word": "μόνος",
        "text": "only"
      },
      {
        "i": 17,
        "word": "ἀλλὰ",
        "text": "but"
      },
      {
        "i": 18,
        "word": "καὶ",
        "text": "also"
      },
      {
        "i": 19,
        "word": "πάντες",
        "text": "all"
      },
      {
        "i": 20,
        "word": "οἱ",
        "text": "those"
      },
      {
        "i": 21,
        "word": "ἐγνωκότες",
        "text": "having known"
      },
      {
        "i": 22,
        "word": "τὴν",
        "text": "the"
      },
      {
        "i": 23,
        "word": "ἀλήθειαν",
        "text": "truth"
      }
    ]
  },
  {
    "verse": [
      {
        "i": 0,
        "word": "διὰ",
        "text": "because of"
      },
      {
        "i": 1,
        "word": "τὴν",
        "text": "the"
      },
      {
        "i": 2,
        "word": "ἀλήθειαν",
        "text": "truth"
      },
      {
        "i": 3,
        "word": "τὴν",
        "text": "-"
      },
      {
        "i": 4,
        "word": "μένουσαν",
        "text": "abiding"
      },
      {
        "i": 5,
        "word": "ἐν",
        "text": "in"
      },
      {
        "i": 6,
        "word": "ἡμῖν",
        "text": "us"
      },
      {
        "i": 7,
        "word": "καὶ",
        "text": "and"
      },
      {
        "i": 8,
        "word": "μεθ’",
        "text": "with"
      },
      {
        "i": 9,
        "word": "ἡμῶν",
        "text": "us"
      },
      {
        "i": 10,
        "word": "ἔσται",
        "text": "that will be"
      },
      {
        "i": 11,
        "word": "εἰς",
        "text": "to"
      },
      {
        "i": 12,
        "word": "τὸν",
        "text": "the"
      },
      {
        "i": 13,
        "word": "αἰῶνα",
        "text": "age"
      }
    ]
  },
  {
    "verse": [
      {
        "i": 0,
        "word": "ἔσται",
        "text": "Will be"
      },
      {
        "i": 1,
        "word": "μεθ’",
        "text": "with"
      },
      {
        "i": 2,
        "word": "ἡμῶν",
        "text": "us"
      },
      {
        "i": 3,
        "word": "χάρις",
        "text": "grace"
      },
      {
        "i": 4,
        "word": "ἔλεος",
        "text": "mercy"
      },
      {
        "i": 5,
        "word": "εἰρήνη",
        "text": "[and] peace"
      },
      {
        "i": 6,
        "word": "παρὰ",
        "text": "from"
      },
      {
        "i": 7,
        "word": "Θεοῦ",
        "text": "God"
      },
      {
        "i": 8,
        "word": "Πατρός",
        "text": "[the] Father"
      },
      {
        "i": 9,
        "word": "καὶ",
        "text": "and"
      },
      {
        "i": 10,
        "word": "παρὰ",
        "text": "from"
      },
      {
        "i": 11,
        "word": "Ἰησοῦ",
        "text": "Jesus"
      },
      {
        "i": 12,
        "word": "Χριστοῦ",
        "text": "Christ"
      },
      {
        "i": 13,
        "word": "τοῦ",
        "text": "the"
      },
      {
        "i": 14,
        "word": "Υἱοῦ",
        "text": "Son"
      },
      {
        "i": 15,
        "word": "τοῦ",
        "text": "of the"
      },
      {
        "i": 16,
        "word": "Πατρός",
        "text": "Father"
      },
      {
        "i": 17,
        "word": "ἐν",
        "text": "in"
      },
      {
        "i": 18,
        "word": "ἀληθείᾳ",
        "text": "truth"
      },
      {
        "i": 19,
        "word": "καὶ",
        "text": "and"
      },
      {
        "i": 20,
        "word": "ἀγάπῃ",
        "text": "love"
      }
    ]
  },
  {
    "verse": [
      {
        "i": 0,
        "word": "Ἐχάρην",
        "text": "I rejoiced"
      },
      {
        "i": 1,
        "word": "λίαν",
        "text": "exceedingly"
      },
      {
        "i": 2,
        "word": "ὅτι",
        "text": "that"
      },
      {
        "i": 3,
        "word": "εὕρηκα",
        "text": "I have found"
      },
      {
        "i": 4,
        "word": "ἐκ",
        "text": "[some] of"
      },
      {
        "i": 5,
        "word": "τῶν",
        "text": "the"
      },
      {
        "i": 6,
        "word": "τέκνων",
        "text": "children"
      },
      {
        "i": 7,
        "word": "σου",
        "text": "of you"
      },
      {
        "i": 8,
        "word": "περιπατοῦντας",
        "text": "walking"
      },
      {
        "i": 9,
        "word": "ἐν",
        "text": "in"
      },
      {
        "i": 10,
        "word": "ἀληθείᾳ",
        "text": "truth"
      },
      {
        "i": 11,
        "word": "καθὼς",
        "text": "just as"
      },
      {
        "i": 12,
        "word": "ἐντολὴν",
        "text": "commandment"
      },
      {
        "i": 13,
        "word": "ἐλάβομεν",
        "text": "we received"
      },
      {
        "i": 14,
        "word": "παρὰ",
        "text": "from"
      },
      {
        "i": 15,
        "word": "τοῦ",
        "text": "the"
      },
      {
        "i": 16,
        "word": "Πατρός",
        "text": "Father"
      }
    ]
  },
  {
    "verse": [
      {
        "i": 0,
        "word": "καὶ",
        "text": "And"
      },
      {
        "i": 1,
        "word": "νῦν",
        "text": "now"
      },
      {
        "i": 2,
        "word": "ἐρωτῶ",
        "text": "I implore"
      },
      {
        "i": 3,
        "word": "σε",
        "text": "you"
      },
      {
        "i": 4,
        "word": "κυρία",
        "text": "lady"
      },
      {
        "i": 5,
        "word": "οὐχ",
        "text": "not"
      },
      {
        "i": 6,
        "word": "ὡς",
        "text": "as"
      },
      {
        "i": 7,
        "word": "ἐντολὴν",
        "text": "a commandment"
      },
      {
        "i": 8,
        "word": "γράφων",
        "text": "I am writing"
      },
      {
        "i": 9,
        "word": "σοι",
        "text": "to you"
      },
      {
        "i": 10,
        "word": "καινὴν",
        "text": "new"
      },
      {
        "i": 11,
        "word": "ἀλλὰ",
        "text": "but"
      },
      {
        "i": 12,
        "word": "ἣν",
        "text": "that which"
      },
      {
        "i": 13,
        "word": "εἴχαμεν",
        "text": "we have had"
      },
      {
        "i": 14,
        "word": "ἀπ’",
        "text": "from"
      },
      {
        "i": 15,
        "word": "ἀρχῆς",
        "text": "[the] beginning"
      },
      {
        "i": 16,
        "word": "ἵνα",
        "text": "that"
      },
      {
        "i": 17,
        "word": "ἀγαπῶμεν",
        "text": "we should love"
      },
      {
        "i": 18,
        "word": "ἀλλήλους",
        "text": "one another"
      }
    ]
  },
  {
    "verse": [
      {
        "i": 0,
        "word": "καὶ",
        "text": "And"
      },
      {
        "i": 1,
        "word": "αὕτη",
        "text": "this"
      },
      {
        "i": 2,
        "word": "ἐστὶν",
        "text": "is"
      },
      {
        "i": 3,
        "word": "ἡ",
        "text": "-"
      },
      {
        "i": 4,
        "word": "ἀγάπη",
        "text": "love"
      },
      {
        "i": 5,
        "word": "ἵνα",
        "text": "that"
      },
      {
        "i": 6,
        "word": "περιπατῶμεν",
        "text": "we should walk"
      },
      {
        "i": 7,
        "word": "κατὰ",
        "text": "according to"
      },
      {
        "i": 8,
        "word": "τὰς",
        "text": "the"
      },
      {
        "i": 9,
        "word": "ἐντολὰς",
        "text": "commandments"
      },
      {
        "i": 10,
        "word": "αὐτοῦ",
        "text": "of Him"
      },
      {
        "i": 11,
        "word": "αὕτη",
        "text": "This"
      },
      {
        "i": 12,
        "word": "ἡ",
        "text": "the"
      },
      {
        "i": 13,
        "word": "ἐντολή",
        "text": "commandment"
      },
      {
        "i": 14,
        "word": "ἐστιν",
        "text": "is"
      },
      {
        "i": 15,
        "word": "καθὼς",
        "text": "just as"
      },
      {
        "i": 16,
        "word": "ἠκούσατε",
        "text": "you have heard"
      },
      {
        "i": 17,
        "word": "ἀπ’",
        "text": "from"
      },
      {
        "i": 18,
        "word": "ἀρχῆς",
        "text": "[the] beginning"
      },
      {
        "i": 19,
        "word": "ἵνα",
        "text": "so that"
      },
      {
        "i": 20,
        "word": "ἐν",
        "text": "in"
      },
      {
        "i": 21,
        "word": "αὐτῇ",
        "text": "it"
      },
      {
        "i": 22,
        "word": "περιπατῆτε",
        "text": "you should walk"
      }
    ]
  },
  {
    "verse": [
      {
        "i": 0,
        "word": "ὅτι",
        "text": "For"
      },
      {
        "i": 1,
        "word": "πολλοὶ",
        "text": "many"
      },
      {
        "i": 2,
        "word": "πλάνοι",
        "text": "deceivers"
      },
      {
        "i": 3,
        "word": "ἐξῆλθον",
        "text": "have entered"
      },
      {
        "i": 4,
        "word": "εἰς",
        "text": "into"
      },
      {
        "i": 5,
        "word": "τὸν",
        "text": "the"
      },
      {
        "i": 6,
        "word": "κόσμον",
        "text": "world"
      },
      {
        "i": 7,
        "word": "οἱ",
        "text": "those"
      },
      {
        "i": 8,
        "word": "μὴ",
        "text": "not"
      },
      {
        "i": 9,
        "word": "ὁμολογοῦντες",
        "text": "confessing"
      },
      {
        "i": 10,
        "word": "Ἰησοῦν",
        "text": "Jesus"
      },
      {
        "i": 11,
        "word": "Χριστὸν",
        "text": "Christ"
      },
      {
        "i": 12,
        "word": "ἐρχόμενον",
        "text": "coming"
      },
      {
        "i": 13,
        "word": "ἐν",
        "text": "in"
      },
      {
        "i": 14,
        "word": "σαρκί",
        "text": "flesh"
      },
      {
        "i": 15,
        "word": "οὗτός",
        "text": "This"
      },
      {
        "i": 16,
        "word": "ἐστιν",
        "text": "is"
      },
      {
        "i": 17,
        "word": "ὁ",
        "text": "the"
      },
      {
        "i": 18,
        "word": "πλάνος",
        "text": "deceiver"
      },
      {
        "i": 19,
        "word": "καὶ",
        "text": "and"
      },
      {
        "i": 20,
        "word": "ὁ",
        "text": "the"
      },
      {
        "i": 21,
        "word": "ἀντίχριστος",
        "text": "antichrist"
      }
    ]
  },
  {
    "verse": [
      {
        "i": 0,
        "word": "βλέπετε",
        "text": "Watch"
      },
      {
        "i": 1,
        "word": "ἑαυτούς",
        "text": "yourselves"
      },
      {
        "i": 2,
        "word": "ἵνα",
        "text": "so that"
      },
      {
        "i": 3,
        "word": "μὴ",
        "text": "not"
      },
      {
        "i": 4,
        "word": "ἀπολέσητε",
        "text": "you should lose"
      },
      {
        "i": 5,
        "word": "ἃ",
        "text": "what things"
      },
      {
        "i": 6,
        "word": "ἠργασάμεθα",
        "text": "we have worked for"
      },
      {
        "i": 7,
        "word": "ἀλλὰ",
        "text": "but"
      },
      {
        "i": 8,
        "word": "μισθὸν",
        "text": "a reward"
      },
      {
        "i": 9,
        "word": "πλήρη",
        "text": "full"
      },
      {
        "i": 10,
        "word": "ἀπολάβητε",
        "text": "you may receive"
      }
    ]
  },
  {
    "verse": [
      {
        "i": 0,
        "word": "πᾶς",
        "text": "Anyone"
      },
      {
        "i": 1,
        "word": "ὁ",
        "text": "-"
      },
      {
        "i": 2,
        "word": "προάγων",
        "text": "going on ahead"
      },
      {
        "i": 3,
        "word": "καὶ",
        "text": "and"
      },
      {
        "i": 4,
        "word": "μὴ",
        "text": "not"
      },
      {
        "i": 5,
        "word": "μένων",
        "text": "abiding"
      },
      {
        "i": 6,
        "word": "ἐν",
        "text": "in"
      },
      {
        "i": 7,
        "word": "τῇ",
        "text": "the"
      },
      {
        "i": 8,
        "word": "διδαχῇ",
        "text": "teaching"
      },
      {
        "i": 9,
        "word": "τοῦ",
        "text": "-"
      },
      {
        "i": 10,
        "word": "Χριστοῦ",
        "text": "of Christ"
      },
      {
        "i": 11,
        "word": "Θεὸν",
        "text": "God"
      },
      {
        "i": 12,
        "word": "οὐκ",
        "text": "not"
      },
      {
        "i": 13,
        "word": "ἔχει",
        "text": "has"
      },
      {
        "i": 14,
        "word": "ὁ",
        "text": "The [one]"
      },
      {
        "i": 15,
        "word": "μένων",
        "text": "abiding"
      },
      {
        "i": 16,
        "word": "ἐν",
        "text": "in"
      },
      {
        "i": 17,
        "word": "τῇ",
        "text": "the"
      },
      {
        "i": 18,
        "word": "διδαχῇ",
        "text": "teaching"
      },
      {
        "i": 19,
        "word": "οὗτος",
        "text": "this [one]"
      },
      {
        "i": 20,
        "word": "καὶ",
        "text": "both"
      },
      {
        "i": 21,
        "word": "τὸν",
        "text": "the"
      },
      {
        "i": 22,
        "word": "Πατέρα",
        "text": "Father"
      },
      {
        "i": 23,
        "word": "καὶ",
        "text": "and"
      },
      {
        "i": 24,
        "word": "τὸν",
        "text": "the"
      },
      {
        "i": 25,
        "word": "Υἱὸν",
        "text": "Son"
      },
      {
        "i": 26,
        "word": "ἔχει",
        "text": "has"
      }
    ]
  },
  {
    "verse": [
      {
        "i": 0,
        "word": "εἴ",
        "text": "If"
      },
      {
        "i": 1,
        "word": "τις",
        "text": "anyone"
      },
      {
        "i": 2,
        "word": "ἔρχεται",
        "text": "comes"
      },
      {
        "i": 3,
        "word": "πρὸς",
        "text": "to"
      },
      {
        "i": 4,
        "word": "ὑμᾶς",
        "text": "you"
      },
      {
        "i": 5,
        "word": "καὶ",
        "text": "and"
      },
      {
        "i": 6,
        "word": "ταύτην",
        "text": "this"
      },
      {
        "i": 7,
        "word": "τὴν",
        "text": "-"
      },
      {
        "i": 8,
        "word": "διδαχὴν",
        "text": "teaching"
      },
      {
        "i": 9,
        "word": "οὐ",
        "text": "not"
      },
      {
        "i": 10,
        "word": "φέρει",
        "text": "does bring"
      },
      {
        "i": 11,
        "word": "μὴ",
        "text": "not"
      },
      {
        "i": 12,
        "word": "λαμβάνετε",
        "text": "receive"
      },
      {
        "i": 13,
        "word": "αὐτὸν",
        "text": "him"
      },
      {
        "i": 14,
        "word": "εἰς",
        "text": "into"
      },
      {
        "i": 15,
        "word": "οἰκίαν",
        "text": "[the] house"
      },
      {
        "i": 16,
        "word": "καὶ",
        "text": "and"
      },
      {
        "i": 17,
        "word": "χαίρειν",
        "text": "to rejoice"
      },
      {
        "i": 18,
        "word": "αὐτῷ",
        "text": "him"
      },
      {
        "i": 19,
        "word": "μὴ",
        "text": "not"
      },
      {
        "i": 20,
        "word": "λέγετε",
        "text": "tell"
      }
    ]
  },
  {
    "verse": [
      {
        "i": 0,
        "word": "ὁ",
        "text": "the [one]"
      },
      {
        "i": 1,
        "word": "λέγων",
        "text": "telling"
      },
      {
        "i": 2,
        "word": "γὰρ",
        "text": "for"
      },
      {
        "i": 3,
        "word": "αὐτῷ",
        "text": "him"
      },
      {
        "i": 4,
        "word": "χαίρειν",
        "text": "to rejoice"
      },
      {
        "i": 5,
        "word": "κοινωνεῖ",
        "text": "partakes"
      },
      {
        "i": 6,
        "word": "τοῖς",
        "text": "in the"
      },
      {
        "i": 7,
        "word": "ἔργοις",
        "text": "works"
      },
      {
        "i": 8,
        "word": "αὐτοῦ",
        "text": "of him"
      },
      {
        "i": 9,
        "word": "τοῖς",
        "text": "-"
      },
      {
        "i": 10,
        "word": "πονηροῖς",
        "text": "evil"
      }
    ]
  },
  {
    "verse": [
      {
        "i": 0,
        "word": "Πολλὰ",
        "text": "Many things"
      },
      {
        "i": 1,
        "word": "ἔχων",
        "text": "having"
      },
      {
        "i": 2,
        "word": "ὑμῖν",
        "text": "to you"
      },
      {
        "i": 3,
        "word": "γράφειν",
        "text": "to write"
      },
      {
        "i": 4,
        "word": "οὐκ",
        "text": "not"
      },
      {
        "i": 5,
        "word": "ἐβουλήθην",
        "text": "I purposed"
      },
      {
        "i": 6,
        "word": "διὰ",
        "text": "with"
      },
      {
        "i": 7,
        "word": "χάρτου",
        "text": "paper"
      },
      {
        "i": 8,
        "word": "καὶ",
        "text": "and"
      },
      {
        "i": 9,
        "word": "μέλανος",
        "text": "ink"
      },
      {
        "i": 10,
        "word": "ἀλλὰ",
        "text": "but"
      },
      {
        "i": 11,
        "word": "ἐλπίζω",
        "text": "I hope"
      },
      {
        "i": 12,
        "word": "γενέσθαι",
        "text": "to come"
      },
      {
        "i": 13,
        "word": "πρὸς",
        "text": "to"
      },
      {
        "i": 14,
        "word": "ὑμᾶς",
        "text": "you"
      },
      {
        "i": 15,
        "word": "καὶ",
        "text": "and"
      },
      {
        "i": 16,
        "word": "στόμα",
        "text": "mouth"
      },
      {
        "i": 17,
        "word": "πρὸς",
        "text": "to"
      },
      {
        "i": 18,
        "word": "στόμα",
        "text": "mouth"
      },
      {
        "i": 19,
        "word": "λαλῆσαι",
        "text": "to speak"
      },
      {
        "i": 20,
        "word": "ἵνα",
        "text": "so that"
      },
      {
        "i": 21,
        "word": "ἡ",
        "text": "the"
      },
      {
        "i": 22,
        "word": "χαρὰ",
        "text": "joy"
      },
      {
        "i": 23,
        "word": "ἡμῶν",
        "text": "of us"
      },
      {
        "i": 24,
        "word": "πεπληρωμένη",
        "text": "having been completed"
      },
      {
        "i": 25,
        "word": "ᾖ",
        "text": "may be"
      }
    ]
  },
  {
    "verse": [
      {
        "i": 0,
        "word": "Ἀσπάζεταί",
        "text": "Greet"
      },
      {
        "i": 1,
        "word": "σε",
        "text": "you"
      },
      {
        "i": 2,
        "word": "τὰ",
        "text": "the"
      },
      {
        "i": 3,
        "word": "τέκνα",
        "text": "children"
      },
      {
        "i": 4,
        "word": "τῆς",
        "text": "of the"
      },
      {
        "i": 5,
        "word": "ἀδελφῆς",
        "text": "sister"
      },
      {
        "i": 6,
        "word": "σου",
        "text": "of you"
      },
      {
        "i": 7,
        "word": "τῆς",
        "text": "-"
      },
      {
        "i": 8,
        "word": "ἐκλεκτῆς",
        "text": "elect"
      }
    ]
  }
]